[{"city":"Vienna","continent":"EUR","order":1,"country":"AUT","ctr_name":"Rathaus Wien","ctr_lat":48.2108,"ctr_lon":16.35784,"cellsanalysed":4381.0,"total_km":392.0776,"covered_km":273.9909,"total_pop":1853160.5009000001,"covered_pop":1579679.5141},{"city":"Graz","continent":"EUR","order":2,"country":"AUT","ctr_name":"Hauptplatz Graz","ctr_lat":47.06955,"ctr_lon":15.43383,"cellsanalysed":1168.0,"total_km":72.978,"covered_km":72.978,"total_pop":260852.5752,"covered_pop":260852.5752},{"city":"Brussels","continent":"EUR","order":1,"country":"BEL","ctr_name":"Brussels Town hall","ctr_lat":50.84642,"ctr_lon":4.35232,"cellsanalysed":3747.0,"total_km":266.2076,"covered_km":234.4322,"total_pop":1378967.355,"covered_pop":1321531.6246},{"city":"Berlin","continent":"EUR","order":1,"country":"DEU","ctr_name":"Old City Hall","ctr_lat":52.51687,"ctr_lon":13.4116,"cellsanalysed":5187.0,"total_km":686.8354,"covered_km":324.645,"total_pop":3265934.7664000001,"covered_pop":1891237.8047},{"city":"Hamburg","continent":"EUR","order":2,"country":"DEU","ctr_name":"Rathaus","ctr_lat":53.55035,"ctr_lon":9.99232,"cellsanalysed":4912.0,"total_km":519.6633,"covered_km":307.4532,"total_pop":1592919.517,"covered_pop":1085424.0519000001},{"city":"Copenhagen","continent":"EUR","order":1,"country":"DNK","ctr_name":"K\u00f8benhavns R\u00e5dhus","ctr_lat":55.67537,"ctr_lon":12.56936,"cellsanalysed":3090.0,"total_km":352.7974,"covered_km":193.5563,"total_pop":1223020.7723000001,"covered_pop":935695.2601},{"city":"Aarhus","continent":"EUR","order":2,"country":"DNK","ctr_name":"Aarhus R\u00e5dhus","ctr_lat":56.1528,"ctr_lon":10.20021,"cellsanalysed":1151.0,"total_km":72.0723,"covered_km":72.0723,"total_pop":208578.9439,"covered_pop":208578.9439},{"city":"Madrid","continent":"EUR","order":1,"country":"ESP","ctr_name":"Ajuntamiento de Madrid","ctr_lat":40.41831,"ctr_lon":-3.6926,"cellsanalysed":4949.0,"total_km":779.6009,"covered_km":308.8202,"total_pop":4888719.7819999997,"covered_pop":2878640.1968999999},{"city":"Barcelona","continent":"EUR","order":2,"country":"ESP","ctr_name":"Ajuntament de Barcelona","ctr_lat":41.38228,"ctr_lon":2.17532,"cellsanalysed":2540.0,"total_km":543.18,"covered_km":158.8194,"total_pop":3823064.1050999998,"covered_pop":2332555.3785000001},{"city":"Paris","continent":"EUR","order":1,"country":"FRA","ctr_name":"H\u00f4tel de Ville","ctr_lat":48.85595,"ctr_lon":2.35167,"cellsanalysed":5178.0,"total_km":1638.2474,"covered_km":324.0474,"total_pop":9685234.8399999999,"covered_pop":4753384.4877000004},{"city":"Marseille","continent":"EUR","order":2,"country":"FRA","ctr_name":"Mairie de Marseille","ctr_lat":43.29657,"ctr_lon":5.36481,"cellsanalysed":2700.0,"total_km":211.8827,"covered_km":168.8907,"total_pop":903670.5704,"covered_pop":823988.5600000001},{"city":"London","continent":"EUR","order":1,"country":"GBR","ctr_name":"City Hall","ctr_lat":51.5055,"ctr_lon":-0.1049,"cellsanalysed":5121.0,"total_km":1841.2089,"covered_km":320.6048,"total_pop":9595697.1853,"covered_pop":3355404.2434},{"city":"Birmingham","continent":"EUR","order":2,"country":"GBR","ctr_name":"Town Hall","ctr_lat":52.47949,"ctr_lon":-1.90372,"cellsanalysed":5101.0,"total_km":668.7039,"covered_km":319.0882,"total_pop":2421750.4605,"covered_pop":1346368.2150999999},{"city":"York","continent":"EUR","order":2,"country":"GBR","ctr_name":"Cliffords Tower","ctr_lat":53.9558,"ctr_lon":-1.08015,"cellsanalysed":640.0,"total_km":40.0658,"covered_km":40.0658,"total_pop":146550.2504,"covered_pop":146550.2504},{"city":"Luxembourg","continent":"EUR","order":1,"country":"LUX","ctr_name":"H\u00f4tel de Ville","ctr_lat":49.61031,"ctr_lon":6.13024,"cellsanalysed":671.0,"total_km":42.0558,"covered_km":42.0558,"total_pop":118802.3158,"covered_pop":118802.3158},{"city":"Amsterdam","continent":"EUR","order":1,"country":"NLD","ctr_name":"Stadsloket Centrum","ctr_lat":52.36822,"ctr_lon":4.9,"cellsanalysed":3761.0,"total_km":345.4439,"covered_km":235.3679,"total_pop":1125519.3599,"covered_pop":907628.1315},{"city":"Utrecht","continent":"EUR","order":2,"country":"NLD","ctr_name":"Stadshuis","ctr_lat":52.09189,"ctr_lon":5.1192,"cellsanalysed":1864.0,"total_km":124.1652,"covered_km":116.6554,"total_pop":444327.7367,"covered_pop":427353.1112},{"city":"Stockholm","continent":"EUR","order":1,"country":"SWE","ctr_name":"Stadshus","ctr_lat":59.32773,"ctr_lon":18.05362,"cellsanalysed":3669.0,"total_km":352.539,"covered_km":230.027,"total_pop":1302139.7747,"covered_pop":982300.8264},{"city":"Gothenburg","continent":"EUR","order":2,"country":"SWE","ctr_name":"B\u00f6rsen G\u00f6teborg","ctr_lat":57.70685,"ctr_lon":11.96466,"cellsanalysed":2637.0,"total_km":179.5716,"covered_km":165.2178,"total_pop":494786.9576,"covered_pop":463521.5341},{"city":"Helsinki","continent":"EUR","order":1,"country":"FIN","ctr_name":"Helsingin kaupungintalo","ctr_lat":60.16812,"ctr_lon":24.95299,"cellsanalysed":2241.0,"total_km":301.0648,"covered_km":140.4709,"total_pop":904590.0474,"covered_pop":533010.7807999999},{"city":"Milan","continent":"EUR","order":1,"country":"ITA","ctr_name":"Comune di Milano","ctr_lat":45.46676,"ctr_lon":9.19041,"cellsanalysed":null,"total_km":753.4897,"covered_km":285.9264,"total_pop":3006098.2941999999,"covered_pop":1693559.6558000001},{"city":"Rome","continent":"EUR","order":2,"country":"ITA","ctr_name":"Municipio Roma I","ctr_lat":41.89018,"ctr_lon":12.48053,"cellsanalysed":null,"total_km":481.7568,"covered_km":286.7405,"total_pop":2339827.0410000002,"covered_pop":1855880.4765999999},{"city":"Oslo","continent":"EUR","order":1,"country":"NOR","ctr_name":"R\u00e5dhuset","ctr_lat":59.91205,"ctr_lon":10.73369,"cellsanalysed":2619.0,"total_km":222.9913,"covered_km":164.141,"total_pop":780239.2398,"covered_pop":641078.8491},{"city":"Warsaw","continent":"EUR","order":2,"country":"POL","ctr_name":"Urz\u0105d Dzielnicy \u015ar\u00f3dmie\u015bcie m. st. Warszawy","ctr_lat":52.22801,"ctr_lon":21.01053,"cellsanalysed":4776.0,"total_km":425.3683,"covered_km":298.759,"total_pop":1785692.6872,"covered_pop":1466915.2825},{"city":"Lisbon","continent":"EUR","order":1,"country":"PRT","ctr_name":"Pa\u00e7os do Concelho - Sede da CML","ctr_lat":38.70815,"ctr_lon":-9.13859,"cellsanalysed":2637.0,"total_km":409.5757,"covered_km":164.4396,"total_pop":1955647.6046,"covered_pop":1006902.2661},{"city":"Bern","continent":"EUR","order":1,"country":"CHE","ctr_name":"Berner Rathaus","ctr_lat":46.9488,"ctr_lon":7.45227,"cellsanalysed":1072.0,"total_km":66.999,"covered_km":66.999,"total_pop":197263.3826,"covered_pop":197263.3826},{"city":"Prague","continent":"EUR","order":1,"country":"CZE","ctr_name":"Magistr\u00e1t Hlavn\u00edho m\u011bsta Prahy","ctr_lat":50.08717,"ctr_lon":14.41784,"cellsanalysed":3833.0,"total_km":295.1211,"covered_km":239.6615,"total_pop":1124028.7586999999,"covered_pop":967202.7927},{"city":"Tallinn","continent":"EUR","order":1,"country":"EST","ctr_name":"Tallinna Kesklinna Valitsus","ctr_lat":59.43938,"ctr_lon":24.74068,"cellsanalysed":1463.0,"total_km":91.6969,"covered_km":91.6969,"total_pop":343666.1708,"covered_pop":343666.1708},{"city":"Budapest","continent":"EUR","order":1,"country":"HUN","ctr_name":"Polg\u00e1rmesteri Hivatal Budapest I. ker\u00fclet","ctr_lat":47.50442,"ctr_lon":19.02881,"cellsanalysed":3638.0,"total_km":433.1167,"covered_km":227.6304,"total_pop":1754341.4335,"covered_pop":1251992.2608},{"city":"Dublin","continent":"EUR","order":1,"country":"IRL","ctr_name":"Dublin City Council","ctr_lat":53.34413,"ctr_lon":-6.27172,"cellsanalysed":3479.0,"total_km":275.2795,"covered_km":217.8559,"total_pop":1002140.0644,"covered_pop":832477.9925000001},{"city":"Riga","continent":"EUR","order":1,"country":"LVA","ctr_name":"R\u012bgas dome","ctr_lat":56.94783,"ctr_lon":24.10638,"cellsanalysed":2556.0,"total_km":165.4403,"covered_km":160.1761,"total_pop":555354.0171000001,"covered_pop":545453.0082},{"city":"Perth","continent":"OCE","order":3,"country":"AUS","ctr_name":"Perth Town Hall","ctr_lat":-31.95662,"ctr_lon":115.86074,"cellsanalysed":5061.0,"total_km":737.1236,"covered_km":315.2148,"total_pop":1253469.6717000001,"covered_pop":548869.5546},{"city":"Sydney","continent":"OCE","order":3,"country":"AUS","ctr_name":"Sydney Town Hall","ctr_lat":-33.87307,"ctr_lon":151.20619,"cellsanalysed":3963.0,"total_km":1249.5498,"covered_km":247.0291,"total_pop":3736597.6527,"covered_pop":1086546.2971000001},{"city":"Melbourne","continent":"OCE","order":3,"country":"AUS","ctr_name":"Melbourne Town Hall","ctr_lat":-37.81513,"ctr_lon":144.96681,"cellsanalysed":4515.0,"total_km":1545.34,"covered_km":281.71,"total_pop":3457293.8489000001,"covered_pop":949785.8745},{"city":"Adelaide","continent":"OCE","order":3,"country":"AUS","ctr_name":"Adelaide Town Hall","ctr_lat":-34.92607,"ctr_lon":138.60017,"cellsanalysed":4184.0,"total_km":482.2468,"covered_km":260.9962,"total_pop":927555.5367000001,"covered_pop":552102.2748},{"city":"Auckland","continent":"OCE","order":3,"country":"NZL","ctr_name":"Auckland Town Hall","ctr_lat":-36.85299,"ctr_lon":174.76338,"cellsanalysed":2612.0,"total_km":403.4268,"covered_km":162.9708,"total_pop":1031244.9195,"covered_pop":457008.1305},{"city":"Wellington","continent":"OCE","order":3,"country":"NZL","ctr_name":"Wellington Town Hall","ctr_lat":-41.28934,"ctr_lon":174.77733,"cellsanalysed":713.0,"total_km":44.5257,"covered_km":44.5257,"total_pop":128174.6001,"covered_pop":128174.6001},{"city":"Mumbai","continent":"ASI","order":3,"country":"IND","ctr_name":"The Asiatic Society of Mumbai Town Hall","ctr_lat":18.93186,"ctr_lon":72.83609,"cellsanalysed":899.0,"total_km":1003.016,"covered_km":55.9176,"total_pop":21745093.9268999994,"covered_pop":2502549.2152},{"city":"Delhi [New Delhi]","continent":"ASI","order":3,"country":"IND","ctr_name":"Ghantaghar Chandni Chowk","ctr_lat":28.65713,"ctr_lon":77.22743,"cellsanalysed":5211.0,"total_km":2465.8772,"covered_km":324.8128,"total_pop":26583416.5379000008,"covered_pop":7543966.9160000002},{"city":"Kuala Lumpur","continent":"ASI","order":3,"country":"MYS","ctr_name":"Dewan Bandaraya Kuala Lumpur","ctr_lat":3.15232,"ctr_lon":101.69397,"cellsanalysed":5159.0,"total_km":1315.1174,"covered_km":320.7468,"total_pop":6322720.6830000002,"covered_pop":2386959.7899000002},{"city":"Toronto","continent":"NAM","order":3,"country":"CAN","ctr_name":"Toronto Old City Hall","ctr_lat":43.65263,"ctr_lon":-79.38175,"cellsanalysed":3516.0,"total_km":2017.4336,"covered_km":219.5945,"total_pop":6023837.8585999999,"covered_pop":1223306.2816999999},{"city":"Montreal","continent":"NAM","order":3,"country":"CAN","ctr_name":"H\u00f4tel de ville de Montr\u00e9al","ctr_lat":45.50891,"ctr_lon":-73.55433,"cellsanalysed":4400.0,"total_km":976.7789,"covered_km":274.8959,"total_pop":3098937.7009999999,"covered_pop":1501831.4683000001},{"city":"Calgary","continent":"NAM","order":3,"country":"CAN","ctr_name":"Calgary City Hall","ctr_lat":51.04603,"ctr_lon":-114.05759,"cellsanalysed":4683.0,"total_km":460.7511,"covered_km":293.1674,"total_pop":1024356.108,"covered_pop":614972.8541},{"city":"New York","continent":"NAM","order":3,"country":"USA","ctr_name":"New York City Hall","ctr_lat":40.71275,"ctr_lon":-74.0061,"cellsanalysed":5211.0,"total_km":5213.657,"covered_km":325.2167,"total_pop":15916462.9818999991,"covered_pop":3493743.0655999999},{"city":"Los Angeles","continent":"NAM","order":3,"country":"USA","ctr_name":"Los Angeles City Hall","ctr_lat":34.053,"ctr_lon":-118.24359,"cellsanalysed":5219.0,"total_km":5539.0133,"covered_km":325.214,"total_pop":14245289.4475999996,"covered_pop":1769524.6973000001},{"city":"Chicago","continent":"NAM","order":3,"country":"USA","ctr_name":"Chicago City Hall","ctr_lat":41.88382,"ctr_lon":-87.63213,"cellsanalysed":3289.0,"total_km":3824.5039,"covered_km":205.2614,"total_pop":6756386.5883999998,"covered_pop":1142005.9129999999},{"city":"Houston","continent":"NAM","order":3,"country":"USA","ctr_name":"Houston City Hall","ctr_lat":29.75998,"ctr_lon":-95.36906,"cellsanalysed":5216.0,"total_km":3395.3951,"covered_km":325.0495,"total_pop":4852413.2873,"covered_pop":620704.4767999999},{"city":"Philadelphia","continent":"NAM","order":3,"country":"USA","ctr_name":"Philadelphia City Hall","ctr_lat":39.95286,"ctr_lon":-75.16447,"cellsanalysed":5167.0,"total_km":1499.8447,"covered_km":322.2978,"total_pop":3122950.8678000001,"covered_pop":1219883.7842000001},{"city":"Phoenix","continent":"NAM","order":4,"country":"USA","ctr_name":"Phoenix City Hall","ctr_lat":33.44866,"ctr_lon":-112.07695,"cellsanalysed":4669.0,"total_km":2296.6012,"covered_km":290.8805,"total_pop":3596291.1553000002,"covered_pop":536914.9541},{"city":"Portland","continent":"NAM","order":4,"country":"USA","ctr_name":"Portland City Hall","ctr_lat":45.51494,"ctr_lon":-122.67897,"cellsanalysed":4750.0,"total_km":946.368,"covered_km":296.7372,"total_pop":1649387.1954000001,"covered_pop":572679.2727},{"city":"San Antonio","continent":"NAM","order":4,"country":"USA","ctr_name":"San Antonio City Hall","ctr_lat":29.42461,"ctr_lon":-98.49522,"cellsanalysed":4387.0,"total_km":871.3206,"covered_km":273.0318,"total_pop":1477978.2901000001,"covered_pop":540374.8441},{"city":"Dallas","continent":"NAM","order":4,"country":"USA","ctr_name":"Dallas City Hall","ctr_lat":32.77638,"ctr_lon":-96.7972,"cellsanalysed":4894.0,"total_km":3689.1553,"covered_km":305.0365,"total_pop":5143325.8147,"covered_pop":498708.8936},{"city":"Mexico City","continent":"NAM","order":3,"country":"MEX","ctr_name":"Antiguo Palacio del Ayuntamiento","ctr_lat":19.43182,"ctr_lon":-99.1341,"cellsanalysed":5217.0,"total_km":2101.3026,"covered_km":324.3511,"total_pop":19525345.5810000002,"covered_pop":4439993.6995999999},{"city":"Buenos Aires","continent":"SAM","order":3,"country":"ARG","ctr_name":"Palacio Municipal de la Ciudad de Buenos Aires","ctr_lat":-34.60828,"ctr_lon":-58.37379,"cellsanalysed":2902.0,"total_km":1942.2748,"covered_km":181.3081,"total_pop":13874444.6832999997,"covered_pop":2526668.3157000002},{"city":"S\u00e3o Paulo","continent":"SAM","order":3,"country":"BRA","ctr_name":"Edif\u00edcio Matarazzo","ctr_lat":-23.5475,"ctr_lon":-46.63726,"cellsanalysed":5211.0,"total_km":1995.5817,"covered_km":324.1642,"total_pop":19099306.5610999987,"covered_pop":3737309.9067000002},{"city":"Rio de Janeiro","continent":"SAM","order":3,"country":"BRA","ctr_name":"C\u00e2mara Municipal do Rio de Janeiro","ctr_lat":-22.90997,"ctr_lon":-43.17665,"cellsanalysed":2007.0,"total_km":1295.1088,"covered_km":124.8542,"total_pop":9789610.5313000008,"covered_pop":1683528.5035999999},{"city":"Salvador","continent":"SAM","order":3,"country":"BRA","ctr_name":"C\u00e2mara Municipal de Salvador","ctr_lat":-12.97494,"ctr_lon":-38.51248,"cellsanalysed":1756.0,"total_km":275.5713,"covered_km":109.0103,"total_pop":3028741.4709000001,"covered_pop":1929734.1313},{"city":"Santiago","continent":"SAM","order":3,"country":"CHL","ctr_name":"Congreso Nacional de Chile sede Santiago","ctr_lat":-33.43836,"ctr_lon":-70.65339,"cellsanalysed":4962.0,"total_km":717.9482,"covered_km":309.3009,"total_pop":6324730.4764,"covered_pop":2506321.9068999998},{"city":"Bogota","continent":"SAM","order":3,"country":"COL","ctr_name":"Palacio de lievano","ctr_lat":4.59854,"ctr_lon":-74.07674,"cellsanalysed":3192.0,"total_km":534.1435,"covered_km":198.0714,"total_pop":8604778.6950000003,"covered_pop":4196905.5711000003}]